odoo8_addon_stock_route_transit-8.0.0.2.0.99.dev1-py2.7-nspkg.pth
odoo_addons/stock_route_transit/__openerp__.py
odoo_addons/stock_route_transit/__init__.py
odoo_addons/stock_route_transit/README.rst
odoo_addons/stock_route_transit/security/groups.xml
odoo_addons/stock_route_transit/view/stock_warehouse.xml
odoo_addons/stock_route_transit/model/stock_warehouse.py
odoo_addons/stock_route_transit/model/__init__.py
odoo_addons/stock_route_transit/model/stock_picking_type.py
odoo_addons/stock_route_transit/test/create_warehouse.yml
odoo_addons/stock_route_transit/test/stock_users.yml
odoo_addons/stock_route_transit/test/purchase_pickings.yml
odoo_addons/stock_route_transit/data/stock_location.xml
odoo_addons/stock_route_transit/static/description/icon.png
odoo8_addon_stock_route_transit-8.0.0.2.0.99.dev1.dist-info/top_level.txt
odoo8_addon_stock_route_transit-8.0.0.2.0.99.dev1.dist-info/WHEEL
odoo8_addon_stock_route_transit-8.0.0.2.0.99.dev1.dist-info/RECORD
odoo8_addon_stock_route_transit-8.0.0.2.0.99.dev1.dist-info/metadata.json
odoo8_addon_stock_route_transit-8.0.0.2.0.99.dev1.dist-info/DESCRIPTION.rst
odoo8_addon_stock_route_transit-8.0.0.2.0.99.dev1.dist-info/METADATA
odoo8_addon_stock_route_transit-8.0.0.2.0.99.dev1.dist-info/namespace_packages.txt
